pyeiscp/__init__.py
pyeiscp/commands.py
pyeiscp/connection.py
pyeiscp/protocol.py
pyeiscp/tools.py
pyeiscp/utils.py
pyeiscp-0.0.7.dist-info/LICENSE
pyeiscp-0.0.7.dist-info/METADATA
pyeiscp-0.0.7.dist-info/WHEEL
pyeiscp-0.0.7.dist-info/entry_points.txt
pyeiscp-0.0.7.dist-info/top_level.txt
pyeiscp-0.0.7.dist-info/zip-safe
pyeiscp-0.0.7.dist-info/RECORD
