Metadata-Version: 2.1
Name: pyeiscp
Version: 0.0.7
Summary: Python API for controlling Anthem Receivers
Home-page: https://github.com/winterscar/python-eiscp
Author: Mathieu Pasquet
Author-email: mat@pyeiscp.pasquet.co
License: LICENSE
Platform: UNKNOWN
Classifier: Development Status :: 5 - Production/Stable
Classifier: Intended Audience :: Developers
Classifier: License :: OSI Approved :: MIT License
Classifier: Operating System :: OS Independent
Classifier: Programming Language :: Python
Classifier: Topic :: Software Development :: Libraries :: Python Modules
License-File: LICENSE
Requires-Dist: netifaces
